problem_bank_scripts/__init__.py
problem_bank_scripts/_vendored/prairielearn.py
problem_bank_scripts/_vendored/python_helper_sympy.py
problem_bank_scripts/attributions.json
problem_bank_scripts/inputs/__init__.py
problem_bank_scripts/inputs/basic.py
problem_bank_scripts/inputs/inputs.py
problem_bank_scripts/inputs/multiple_choice.py
problem_bank_scripts/inputs/utils.py
problem_bank_scripts/prairielearn.py
problem_bank_scripts/problem_bank_scripts.py
problem_bank_scripts/qti_export.py
problem_bank_scripts/scripts/check_question.py
problem_bank_scripts/scripts/check_server_ast.py
problem_bank_scripts/scripts/cli.py
problem_bank_scripts/scripts/lint_server.py
problem_bank_scripts/scripts/process.py
problem_bank_scripts/scripts/process_q.py
problem_bank_scripts/tui/__init__.py
problem_bank_scripts/tui/__main__.py
problem_bank_scripts/tui/generate_questions.py
problem_bank_scripts/tui/gpt.py
problem_bank_scripts/tui/inputs.py
problem_bank_scripts/tui/known_questions/openstax-stats-2e.json
problem_bank_scripts/tui/main.py
problem_bank_scripts/tui/question.md.template
problem_bank_scripts/tui/scrap-openstax/fixText.ts
problem_bank_scripts/tui/scrap-openstax/openstax.ts
problem_bank_scripts/tui/scrap-openstax/utils.ts
problem_bank_scripts/tui/similarity.py
problem_bank_scripts/tui/tui.py
problem_bank_scripts/tui/utils.py
problem_bank_scripts/tui/write_md.py
problem_bank_scripts/webwork_to_md.py
problem_bank_scripts-1.0.2.dist-info/LICENSE
problem_bank_scripts-1.0.2.dist-info/METADATA
problem_bank_scripts-1.0.2.dist-info/WHEEL
problem_bank_scripts-1.0.2.dist-info/entry_points.txt
problem_bank_scripts-1.0.2.dist-info/RECORD
