Metadata-Version: 2.1
Name: problem_bank_scripts
Version: 1.0.2
Summary: A package with useful functions to convert between different problem bank formats.
Home-page: https://github.com/open-resources/problem_bank_scripts
License: MIT
Author: Open Problem Bank Team
Requires-Python: >=3.10
Classifier: License :: OSI Approved :: MIT License
Classifier: Programming Language :: Python :: 3
Classifier: Programming Language :: Python :: 3.10
Classifier: Programming Language :: Python :: 3.11
Classifier: Programming Language :: Python :: 3.12
Provides-Extra: docs
Provides-Extra: tests
Provides-Extra: tui
Requires-Dist: PyYAML (>=6.0.2,<7.0.0)
Requires-Dist: Sphinx (>=7.4.7,<8.0.0) ; extra == "docs"
Requires-Dist: black (>=24.8.0,<25.0.0)
Requires-Dist: exceptiongroup (>=1.2.2,<2.0.0) ; python_version < "3.11"
Requires-Dist: fastjsonschema (>=2.20.0,<3.0.0) ; extra == "tests"
Requires-Dist: gitpython (>=3.1.43,<4.0.0)
Requires-Dist: ipykernel (>=6.29.5,<7.0.0) ; extra == "docs"
Requires-Dist: markdown-it-py (>=3.0.0,<4.0.0)
Requires-Dist: mdformat (>=0.7.14,<0.8.0)
Requires-Dist: myst-nb (>=1.1.1,<2.0.0) ; extra == "docs"
Requires-Dist: myst-parser (>=3.0.1,<4.0.0) ; extra == "docs"
Requires-Dist: nbsphinx (>=0.8.5,<0.9.0) ; extra == "docs"
Requires-Dist: nltk (>=3.8.1,<4.0.0) ; extra == "tui"
Requires-Dist: numpy (>=1.26.4,<2.0.0)
Requires-Dist: openai (>=1.40.1,<2.0.0) ; extra == "tui"
Requires-Dist: pandas (>=2.2.2,<3.0.0)
Requires-Dist: pdf2image (>=1.17.0,<2.0.0) ; extra == "tui"
Requires-Dist: problem-bank-helpers (>=0.3.2,<0.4.0)
Requires-Dist: pytest (>=8.3.2,<9.0.0) ; extra == "tests"
Requires-Dist: pytest-subtests (>=0.13.1,<0.14.0) ; extra == "tests"
Requires-Dist: python-dotenv (>=1.0.1,<2.0.0) ; extra == "tui"
Requires-Dist: questionary (>=2.0.1,<3.0.0) ; extra == "tui"
Requires-Dist: scikit-learn (>=1.5.1,<2.0.0) ; extra == "tui"
Requires-Dist: sphinx-rtd-theme (>=2.0.0,<3.0.0) ; extra == "docs"
Requires-Dist: sympy (>=1.13.2,<2.0.0)
Requires-Dist: typing-extensions (>=4.12.2,<5.0.0)
Project-URL: Documentation, https://problem_bank_scripts.readthedocs.io/en/latest/
Project-URL: Repository, https://github.com/open-resources/problem_bank_scripts
